seven2one/questra/data/__init__.py
seven2one/questra/data/client.py
seven2one/questra/data/exceptions.py
seven2one/questra/data/highlevel_client.py
seven2one/questra/data/managers.py
seven2one/questra/data/rest_transport.py
seven2one/questra/data/results.py
seven2one/questra/data/transport.py
seven2one/questra/data/generated/README.md
seven2one/questra/data/generated/__init__.py
seven2one/questra/data/generated/models.py
seven2one/questra/data/generated/rest_models.py
seven2one/questra/data/models/__init__.py
seven2one/questra/data/models/common.py
seven2one/questra/data/models/inputs.py
seven2one/questra/data/models/inventory.py
seven2one/questra/data/models/namespace.py
seven2one/questra/data/models/permissions.py
seven2one/questra/data/models/rest.py
seven2one/questra/data/models/role.py
seven2one/questra/data/models/system.py
seven2one/questra/data/models/timeseries.py
seven2one/questra/data/operations/__init__.py
seven2one/questra/data/operations/dynamic_inventory.py
seven2one/questra/data/operations/mutations.py
seven2one/questra/data/operations/queries.py
seven2one/questra/data/operations/rest_audit.py
seven2one/questra/data/operations/rest_file.py
seven2one/questra/data/operations/rest_timeseries.py
seven2one_questra_data-0.8.1.dist-info/METADATA
seven2one_questra_data-0.8.1.dist-info/WHEEL
seven2one_questra_data-0.8.1.dist-info/RECORD
