Metadata-Version: 2.4
Name: seven2one-questra-data
Version: 0.8.1
Summary: Python client for Questra Data with high-level API, type-safe dataclasses, and optional pandas integration for user-defined data models and timeseries management
Author-email: Jürgen Talasch <juergen.talasch@seven2one.de>
License: Proprietary
Classifier: Development Status :: 4 - Beta
Classifier: Intended Audience :: Developers
Classifier: Intended Audience :: Information Technology
Classifier: Intended Audience :: Science/Research
Classifier: License :: Other/Proprietary License
Classifier: Programming Language :: Python :: 3
Classifier: Programming Language :: Python :: 3.10
Classifier: Programming Language :: Python :: 3.11
Classifier: Programming Language :: Python :: 3.12
Classifier: Programming Language :: Python :: 3.13
Classifier: Programming Language :: Python :: 3.14
Classifier: Topic :: Database
Classifier: Topic :: Scientific/Engineering :: Information Analysis
Classifier: Topic :: Software Development :: Libraries :: Python Modules
Classifier: Typing :: Typed
Requires-Python: >=3.10
Requires-Dist: gql<4.0.0,>=3.5.0
Requires-Dist: requests-toolbelt<2.0.0,>=1.0.0
Requires-Dist: requests<3.0.0,>=2.31.0
Requires-Dist: seven2one-questra-authentication>=0.2.3
Provides-Extra: pandas
Requires-Dist: pandas>=2.0.0; extra == 'pandas'
